tap_airtable/__init__.py
tap_airtable/client.py
tap_airtable/entities.py
tap_airtable/streams.py
tap_airtable/tap.py
tap_airtable/tests/__init__.py
tap_airtable/tests/test_tap.py
tap_airtable/types.py
tap_airtable-0.1.0.dist-info/LICENSE.md
tap_airtable-0.1.0.dist-info/METADATA
tap_airtable-0.1.0.dist-info/WHEEL
tap_airtable-0.1.0.dist-info/entry_points.txt
tap_airtable-0.1.0.dist-info/RECORD
