Metadata-Version: 2.1
Name: tap-airtable
Version: 0.1.0
Summary: tap-airtable is a Singer tap for Airtable, built with the Meltano SDK for Singer Taps.
License: Apache 2.0
Keywords: ELT,Airtable
Author: Tomas Votava
Requires-Python: >=3.9,<3.12
Classifier: License :: Other/Proprietary License
Classifier: Programming Language :: Python :: 3
Classifier: Programming Language :: Python :: 3.9
Classifier: Programming Language :: Python :: 3.10
Classifier: Programming Language :: Python :: 3.11
Requires-Dist: backoff (>=2.2.1,<3.0.0)
Requires-Dist: python-slugify (>=8.0.4,<9.0.0)
Requires-Dist: requests (>=2.31.0,<3.0.0)
Requires-Dist: singer-sdk
